ai_workspace/__init__.py
ai_workspace/database/__init__.py
ai_workspace/database/base.py
ai_workspace/database/mongo.py
ai_workspace/database/qdrant.py
ai_workspace/exceptions/__init__.py
ai_workspace/exceptions/errors/__init__.py
ai_workspace/exceptions/errors/database.py
ai_workspace/exceptions/errors/workspace.py
ai_workspace/exceptions/handlers/__init__.py
ai_workspace/exceptions/handlers/workspace.py
ai_workspace/packages/__init__.py
ai_workspace/packages/base.py
ai_workspace/packages/cost.py
ai_workspace/packages/document.py
ai_workspace/packages/embed.py
ai_workspace/packages/workspace.py
ai_workspace/schemas/__init__.py
ai_workspace/schemas/base.py
ai_workspace/schemas/cost.py
ai_workspace/schemas/document.py
ai_workspace/schemas/workspace.py
ai_workspace/utils/logger.py
openedu_ai_workspace-0.1.37.dist-info/METADATA
openedu_ai_workspace-0.1.37.dist-info/WHEEL
openedu_ai_workspace-0.1.37.dist-info/top_level.txt
openedu_ai_workspace-0.1.37.dist-info/RECORD
